{
  "id": "02ad52ce2c70",
  "agent": "ccc-oracle1-check",
  "room": "harbor",
  "tool": "shell",
  "command": "git -C /home/ubuntu/.openclaw/workspace show --stat 7ed83ba | head -n 30",
  "cwd": "/home/ubuntu/.openclaw/workspace",
  "started": 1776887115.9409986,
  "status": "completed",
  "output": "commit 7ed83ba32335e4b29209b288731f29386137f9b1\nAuthor: superinstance <superinstance@users.noreply.github.com>\nDate:   Wed Apr 22 18:23:03 2026 +0000\n\n    \ud83c\udfa3\ud83d\udcda Domain-specific apps: FishingLog + StudyLog\n    \n    New web terminal routes:\n    - /fishinglog \u2014 catch logging with species, weight, location, conditions\n    - /studylog \u2014 study session tracker with timer, confidence scoring\n    \n    Both apps:\n    - localStorage persistence (works offline)\n    - PLATO tile submission (sends insights to fleet)\n    - Dark theme, mobile responsive\n    \n    FishingLog features:\n    - Species datalist (10 Alaskan species)\n    - Weight/count, location, depth, temp, tide, moon phase, bait/gear\n    - History view with catch entries\n    - Stats: total catches, total weight, species count, best catch\n    \n    StudyLog features:\n    - Pomodoro-style timer (start/pause/reset)\n    - Session logging with subject, duration, method, insight, confidence\n    - 7 study methods: reading, practice, video, tutorial, flashcards, teaching, project\n    - History view with confidence tracking\n\n data/crab-trap/agent-registry.jsonl |   1 +\n data/fishinglog-app.html            | 172 ++++++++++++++++++++++++++++++++++++\n data/studylog-app.html              | 169 +++++++++++++++++++++++++++++++++++\n",
  "error": "",
  "returncode": 0,
  "completed": 1776887115.9452872,
  "duration": 0.0
}